CHANGELOG.md
starlite_sessions/__init__.py
starlite_sessions/py.typed
starlite_sessions/session_auth.py
starlite_sessions-1.2.0.dist-info/LICENSE
starlite_sessions-1.2.0.dist-info/WHEEL
starlite_sessions-1.2.0.dist-info/METADATA
starlite_sessions-1.2.0.dist-info/RECORD
